helmion/__init__.py
helmion/chart.py
helmion/config.py
helmion/data.py
helmion/exception.py
helmion/helmchart.py
helmion/info.py
helmion/processor.py
helmion/resource.py
helmion/util.py
helmion/tests/__init__.py
helmion/tests/test_chart.py
helmion/tests/test_helmchart.py
helmion/tests/test_info.py
helmion/tests/test_slow.py
helmion/tests/test_util.py
helmion-0.8.6.dist-info/LICENSE
helmion-0.8.6.dist-info/METADATA
helmion-0.8.6.dist-info/WHEEL
helmion-0.8.6.dist-info/top_level.txt
helmion-0.8.6.dist-info/RECORD
