Metadata-Version: 2.1
Name: helmion
Version: 0.8.6
Summary: Helmion
Home-page: https://github.com/RangelReale/helmion
Author: Rangel Reale
Author-email: rangelreale@gmail.com
License: UNKNOWN
Platform: UNKNOWN
Classifier: Programming Language :: Python :: 3
Classifier: License :: OSI Approved :: MIT License
Classifier: Operating System :: OS Independent
Requires-Python: >=3.6
Requires-Dist: PyYAML (>=5.3.1)
Requires-Dist: requests (>=2.25.0)
Requires-Dist: jsonpatchext (>=1.37)
Requires-Dist: python-dateutil (>=2.8.1)
Requires-Dist: semantic-version (>=2.8.5)
Requires-Dist: deepmerge (>=0.1)
